mcp_okx/__init__.py
mcp_okx/__main__.py
mcp_okx/account.py
mcp_okx/config.py
mcp_okx/market.py
mcp_okx/trading.py
mcp_okx-0.1.0.dist-info/METADATA
mcp_okx-0.1.0.dist-info/WHEEL
mcp_okx-0.1.0.dist-info/entry_points.txt
mcp_okx-0.1.0.dist-info/licenses/LICENSE
mcp_okx-0.1.0.dist-info/RECORD
