Metadata-Version: 2.4
Name: mcp-okx
Version: 0.1.0
Summary: OKX MCP Server
Project-URL: Repository, https://github.com/aahl/mcp-okx
License: MIT
License-File: LICENSE
Keywords: llm,mcp
Requires-Python: >=3.10
Requires-Dist: fastmcp>=2.0.0
Requires-Dist: python-okx>=0.4.0
